functionalfilet/ENN_net.py
functionalfilet/__init__.py
functionalfilet/graph_eat.py
functionalfilet/graph_gen.py
functionalfilet/model.py
functionalfilet/pRNN_net.py
functionalfilet/utils.py
functionalfilet-0.5.2.dist-info/DESCRIPTION.rst
functionalfilet-0.5.2.dist-info/METADATA
functionalfilet-0.5.2.dist-info/RECORD
functionalfilet-0.5.2.dist-info/WHEEL
functionalfilet-0.5.2.dist-info/metadata.json
functionalfilet-0.5.2.dist-info/top_level.txt
