Metadata-Version: 2.0
Name: functionalfilet
Version: 0.5.2
Summary: Evolutionnary Neural Network Model with PyTorch
Home-page: UNKNOWN
Author: FabienFrfr (Fabien Furfaro)
Author-email: <fabien.furfaro@gmail.com>
License: UNKNOWN
Keywords: python,pytorch,graph,machine learning,evolution
Platform: UNKNOWN
Classifier: Development Status :: 1 - Planning
Classifier: Intended Audience :: Developers
Classifier: Programming Language :: Python :: 3
Classifier: Operating System :: Unix
Classifier: Operating System :: MacOS :: MacOS X
Classifier: Operating System :: Microsoft :: Windows
Requires-Dist: numpy
Requires-Dist: pandas
Requires-Dist: torch
Requires-Dist: torchvision
Requires-Dist: matplotlib
Requires-Dist: networkx
Requires-Dist: tqdm
Requires-Dist: scikit-learn
Requires-Dist: scikit-datasets
Requires-Dist: seaborn
Requires-Dist: gym
